networking_mlnx_baremetal/__init__.py
networking_mlnx_baremetal/_i18n.py
networking_mlnx_baremetal/constants.py
networking_mlnx_baremetal/exceptions.py
networking_mlnx_baremetal/ironic_client.py
networking_mlnx_baremetal/ufm_client.py
networking_mlnx_baremetal/plugins/__init__.py
networking_mlnx_baremetal/plugins/ml2/__init__.py
networking_mlnx_baremetal/plugins/ml2/config.py
networking_mlnx_baremetal/plugins/ml2/mech_ib_baremetal.py
networking_mlnx_baremetal/plugins/ml2/bind-port/1.create-new-normal-port.json
networking_mlnx_baremetal/plugins/ml2/bind-port/2.update-new-created-port-mac.json
networking_mlnx_baremetal/plugins/ml2/bind-port/3.bind-port-to-node.json
networking_mlnx_baremetal/plugins/ml2/bind-port/3.bind-segments.json
networking_mlnx_baremetal/plugins/ml2/bind-port/4.update-port-vif-bind-type.log
networking_mlnx_baremetal/plugins/ml2/bind-port/5.enable-dhcp-for-port.json
networking_mlnx_baremetal/plugins/ml2/bind-port/bind.log
networking_mlnx_baremetal/plugins/ml2/unbind-port/1.origin-port.json
networking_mlnx_baremetal/plugins/ml2/unbind-port/2.detach-port-from-node.json
networking_mlnx_baremetal/plugins/ml2/unbind-port/3.update-port-mac-vif.json
networking_mlnx_baremetal/plugins/ml2/unbind-port/delete.log
networking_mlnx_baremetal/tests/__init__.py
networking_mlnx_baremetal/tests/base.py
networking_mlnx_baremetal/ufmclient/__init__.py
networking_mlnx_baremetal/ufmclient/client.py
networking_mlnx_baremetal/ufmclient/constants.py
networking_mlnx_baremetal/ufmclient/exceptions.py
networking_mlnx_baremetal/ufmclient/readme.rst
networking_mlnx_baremetal/ufmclient/session.py
networking_mlnx_baremetal/ufmclient/utils.py
networking_mlnx_baremetal/ufmclient/modules/__init__.py
networking_mlnx_baremetal/ufmclient/modules/base.py
networking_mlnx_baremetal/ufmclient/modules/resources/__init__.py
networking_mlnx_baremetal/ufmclient/modules/resources/pkey.py
networking_mlnx_baremetal-1.0.2.dist-info/AUTHORS
networking_mlnx_baremetal-1.0.2.dist-info/LICENSE
networking_mlnx_baremetal-1.0.2.dist-info/METADATA
networking_mlnx_baremetal-1.0.2.dist-info/WHEEL
networking_mlnx_baremetal-1.0.2.dist-info/entry_points.txt
networking_mlnx_baremetal-1.0.2.dist-info/pbr.json
networking_mlnx_baremetal-1.0.2.dist-info/top_level.txt
networking_mlnx_baremetal-1.0.2.dist-info/RECORD
